adbPullAs/VERSION
adbPullAs/__init__.py
adbPullAs-2.0.0.dist-info/LICENSE
adbPullAs-2.0.0.dist-info/METADATA
adbPullAs-2.0.0.dist-info/WHEEL
adbPullAs-2.0.0.dist-info/entry_points.txt
adbPullAs-2.0.0.dist-info/top_level.txt
adbPullAs-2.0.0.dist-info/RECORD
