Metadata-Version: 2.1
Name: adbPullAs
Version: 2.0.0
Summary: adb pull wrapper to pull package private files from Android device
Home-page: https://github.com/ViliusSutkus89/adbPullAs/
Author: Vilius Sutkus '89
Author-email: ViliusSutkus89@gmail.com
License: GPLv3
Project-URL: Tracker, https://github.com/ViliusSutkus89/adbPullAs/issues
Keywords: adb pull run-as
Classifier: Development Status :: 5 - Production/Stable
Classifier: Environment :: Console
Classifier: Intended Audience :: Developers
Classifier: License :: OSI Approved :: GNU General Public License v3 (GPLv3)
Classifier: Natural Language :: English
Classifier: Operating System :: Android
Classifier: Programming Language :: Python :: 3
Classifier: Programming Language :: Python :: 3.9
Classifier: Topic :: Utilities
Requires-Python: >=3.9
License-File: LICENSE
